openvk_api/__init__.py
openvk_api/base_client.py
openvk_api/consts.py
openvk_api/exceptions.py
openvk_api-0.0.3.dist-info/LICENSE
openvk_api-0.0.3.dist-info/WHEEL
openvk_api-0.0.3.dist-info/METADATA
openvk_api-0.0.3.dist-info/RECORD
