Metadata-Version: 2.1
Name: openvk-api
Version: 0.0.3
Summary: openvk api based on httpx
Home-page: https://github.com/NoPlagiarism/openvk-api
License: MIT
Keywords: openvk,httpx
Author: NoPlagiarism
Author-email: 37241775+NoPlagiarism@users.noreply.github.com
Requires-Python: >=3.9,<4.0
Classifier: Development Status :: 2 - Pre-Alpha
Classifier: License :: OSI Approved :: MIT License
Classifier: Programming Language :: Python :: 3
Classifier: Programming Language :: Python :: 3.10
Classifier: Programming Language :: Python :: 3.9
Requires-Dist: httpx (>=0.23.1,<0.24.0)
Project-URL: Repository, https://github.com/NoPlagiarism/openvk-api
